useful_prints/__init__.py
useful_prints/_version.py
useful_prints/dict_printer.py
useful_prints/list_printer.py
useful_prints/percentage.py
useful_prints-0.0.0.dist-info/LICENSE
useful_prints-0.0.0.dist-info/METADATA
useful_prints-0.0.0.dist-info/WHEEL
useful_prints-0.0.0.dist-info/top_level.txt
useful_prints-0.0.0.dist-info/RECORD
